japr/check.py
japr/check_providers/__init__.py
japr/check_providers/ci_check_provider.py
japr/check_providers/contributing_check_provider.py
japr/check_providers/csharp_check_provider.py
japr/check_providers/git_check_provider.py
japr/check_providers/github_check_provider.py
japr/check_providers/javascript_check_provider.py
japr/check_providers/license_check_provider.py
japr/check_providers/python_check_provider.py
japr/check_providers/readme_check_provider.py
japr/check_providers/rust_check_provider.py
japr/check_providers/shell_check_provider.py
japr/check_providers/terraform_check_provider.py
japr/japr.py
japr/template_util.py
japr/templates/CONTRIBUTING.md
japr/templates/README.md
japr/templates/bug_report_issue_template.md
japr/templates/feature_request_issue_template.md
japr/templates/pull_request_template.md
japr/util.py
japr-1.4.2.dist-info/LICENSE.md
japr-1.4.2.dist-info/METADATA
japr-1.4.2.dist-info/WHEEL
japr-1.4.2.dist-info/entry_points.txt
japr-1.4.2.dist-info/RECORD
